pytube/__init__.py
pytube/__main__.py
pytube/captions.py
pytube/cipher.py
pytube/cli.py
pytube/exceptions.py
pytube/extract.py
pytube/helpers.py
pytube/innertube.py
pytube/itags.py
pytube/metadata.py
pytube/monostate.py
pytube/parser.py
pytube/query.py
pytube/request.py
pytube/streams.py
pytube/version.py
pytube/contrib/__init__.py
pytube/contrib/channel.py
pytube/contrib/playlist.py
pytube/contrib/search.py
pytubefixaugust24-15.0.0.dist-info/LICENSE
pytubefixaugust24-15.0.0.dist-info/METADATA
pytubefixaugust24-15.0.0.dist-info/WHEEL
pytubefixaugust24-15.0.0.dist-info/entry_points.txt
pytubefixaugust24-15.0.0.dist-info/top_level.txt
pytubefixaugust24-15.0.0.dist-info/zip-safe
pytubefixaugust24-15.0.0.dist-info/RECORD
